src/fsm_controller.v
// FSM controller pentru cache 4-way set-associative
// Stari: IDLE → CHECK_HIT → READ_HIT/WRITE_HIT/EVICT → ALLOCATE_FETCH → COMPLETE → IDLE
// Write policy: write-back + write-allocate

module fsm_controller (
    input  wire clk,
    input  wire rst,

    // Status inputs de la datapath
    input  wire cpu_valid,      // CPU are un request activ
    input  wire cpu_write,      // tipul requestului (1=write, 0=read)
    input  wire cache_hit,      // tag match + valid gasit
    input  wire is_dirty,       // way-ul LRU e dirty (necesita evict)
    input  wire mem_ready,      // memoria principala a terminat operatia

    // Semnale de control catre datapath
    output reg  latch_request,  // latchez addr/data de la CPU
    output reg  do_cache_write, // scrie un bloc in cache_memory
    output reg  do_mem_read,    // initiaza citire din memoria principala
    output reg  do_mem_write,   // initiaza scriere in memoria principala (evict)
    output reg  update_lru,     // actualizeaza LRU tracker dupa acces
    output reg  set_dirty,      // seteaza bitul dirty la scriere in cache
    output reg  cpu_ready,      // CPU poate avansa (stall release)

    output wire [2:0] state_out // starea curenta (pentru debug si datapath)
);

    // Encodarea starilor
    localparam IDLE           = 3'd0;
    localparam CHECK_HIT      = 3'd1;
    localparam READ_HIT       = 3'd2;
    localparam WRITE_HIT      = 3'd3;
    localparam EVICT          = 3'd4;
    localparam ALLOCATE_FETCH = 3'd5;
    localparam COMPLETE       = 3'd6;

    reg [2:0] state, next_state;
    reg       pending_write;    // tipul operatiei retinute (0=read, 1=write)

    assign state_out = state;

    // ---------- Registru de stare (secvential) ----------
    always @(posedge clk) begin
        if (rst) begin
            state         <= IDLE;
            pending_write <= 1'b0;
        end else begin
            state <= next_state;
            // retine tipul operatiei la prima tranzitie din IDLE
            if (state == IDLE && cpu_valid)
                pending_write <= cpu_write;
        end
    end

    // ---------- Logica next-state + semnale de control (combinational) ----------
    always @(*) begin
        // valori default: nimic activ, ramanem in starea curenta
        next_state     = state;
        latch_request  = 1'b0;
        do_cache_write = 1'b0;
        do_mem_read    = 1'b0;
        do_mem_write   = 1'b0;
        update_lru     = 1'b0;
        set_dirty      = 1'b0;
        cpu_ready      = 1'b0;

        case (state)

            // Asteptam request de la CPU
            IDLE: begin
                if (cpu_valid) begin
                    latch_request = 1'b1;  // latchez adresa si data
                    next_state    = CHECK_HIT;
                end
            end

            // Verificam daca blocul e in cache
            CHECK_HIT: begin
                if (cache_hit)
                    next_state = pending_write ? WRITE_HIT : READ_HIT;
                else
                    next_state = is_dirty ? EVICT : ALLOCATE_FETCH;
            end

            // Hit la citire: servim CPU direct din cache
            READ_HIT: begin
                update_lru = 1'b1;
                cpu_ready  = 1'b1;
                next_state = IDLE;
            end

            // Hit la scriere: modificam blocul in cache (write-back)
            WRITE_HIT: begin
                do_cache_write = 1'b1;
                set_dirty      = 1'b1;
                update_lru     = 1'b1;
                cpu_ready      = 1'b1;
                next_state     = IDLE;
            end

            // Miss + way LRU dirty: scriem blocul vechi in memoria principala
            EVICT: begin
                do_mem_write = 1'b1;
                if (mem_ready)
                    next_state = ALLOCATE_FETCH;
                // altfel asteptam (mem_ready = 0 => wait-state)
            end

            // Aducem blocul nou din memoria principala
            ALLOCATE_FETCH: begin
                do_mem_read = 1'b1;
                if (mem_ready)
                    next_state = COMPLETE;
            end

            // Blocul a ajuns din memorie; il scriem in cache si servim CPU
            COMPLETE: begin
                do_cache_write = 1'b1;
                // write-allocate: dirty doar daca operatia era o scriere
                set_dirty      = pending_write;
                update_lru     = 1'b1;
                cpu_ready      = 1'b1;
                next_state     = IDLE;
            end

            default: next_state = IDLE;

        endcase
    end

endmodule

tb/tb_fsm_controller.v
// Testbench pentru fsm_controller
// Scenarii testate:
//   1. Read hit:  IDLE → CHECK_HIT → READ_HIT → IDLE
//   2. Write hit: IDLE → CHECK_HIT → WRITE_HIT → IDLE
//   3. Read miss (clean way): IDLE → CHECK_HIT → ALLOCATE_FETCH → COMPLETE → IDLE
//   4. Read miss (dirty way): IDLE → CHECK_HIT → EVICT → ALLOCATE_FETCH → COMPLETE → IDLE

`timescale 1ns/1ps

module tb_fsm_controller;

    // Ceas si reset
    reg clk, rst;

    // Inputs FSM
    reg cpu_valid, cpu_write;
    reg cache_hit, is_dirty, mem_ready;

    // Outputs FSM
    wire latch_request, do_cache_write, do_mem_read, do_mem_write;
    wire update_lru, set_dirty, cpu_ready;
    wire [2:0] state_out;

    // Instantiere DUT
    fsm_controller dut (
        .clk           (clk),
        .rst           (rst),
        .cpu_valid     (cpu_valid),
        .cpu_write     (cpu_write),
        .cache_hit     (cache_hit),
        .is_dirty      (is_dirty),
        .mem_ready     (mem_ready),
        .latch_request (latch_request),
        .do_cache_write(do_cache_write),
        .do_mem_read   (do_mem_read),
        .do_mem_write  (do_mem_write),
        .update_lru    (update_lru),
        .set_dirty     (set_dirty),
        .cpu_ready     (cpu_ready),
        .state_out     (state_out)
    );

    // Generare ceas: 10 ns perioada
    initial clk = 0;
    always #5 clk = ~clk;

    // Taskuri ajutatoare
    task tick;
        input integer n;
        integer k;
        begin
            for (k = 0; k < n; k = k + 1)
                @(posedge clk); #1;
        end
    endtask

    task show;
        input [127:0] label;
        begin
            $display("[%0t] %s | state=%0d | cpu_ready=%b latch=%b cache_wr=%b mem_rd=%b mem_wr=%b upd_lru=%b dirty=%b",
                $time, label, state_out, cpu_ready, latch_request,
                do_cache_write, do_mem_read, do_mem_write, update_lru, set_dirty);
        end
    endtask

    initial begin
        $dumpfile("waves/tb_fsm.vcd");
        $dumpvars(0, tb_fsm_controller);

        // ---------- Reset ----------
        rst = 1; cpu_valid = 0; cpu_write = 0;
        cache_hit = 0; is_dirty = 0; mem_ready = 0;
        tick(2);
        rst = 0;
        $display("--- RESET done ---");

        // ========================================================
        // Scenariu 1: READ HIT
        // ========================================================
        $display("\n--- Scenariu 1: READ HIT ---");
        cpu_valid = 1; cpu_write = 0;
        cache_hit = 1; is_dirty = 0;
        show("IDLE+req ");
        tick(1); show("CHECK_HIT");  // trebuie sa fim in CHECK_HIT
        tick(1); show("READ_HIT ");  // servire + cpu_ready=1
        tick(1); show("IDLE     ");  // inapoi in IDLE
        cpu_valid = 0;
        tick(1);

        // ========================================================
        // Scenariu 2: WRITE HIT
        // ========================================================
        $display("\n--- Scenariu 2: WRITE HIT ---");
        cpu_valid = 1; cpu_write = 1;
        cache_hit = 1; is_dirty = 0;
        tick(1); show("CHECK_HIT");
        tick(1); show("WRITE_HIT");  // do_cache_write=1, set_dirty=1, cpu_ready=1
        tick(1); show("IDLE     ");
        cpu_valid = 0; cpu_write = 0;
        tick(1);

        // ========================================================
        // Scenariu 3: READ MISS, way curat
        // ========================================================
        $display("\n--- Scenariu 3: READ MISS (clean way) ---");
        cpu_valid = 1; cpu_write = 0;
        cache_hit = 0; is_dirty = 0;
        tick(1); show("CHECK_HIT    ");
        tick(1); show("ALLOC_FETCH  ");  // do_mem_read=1
        // simulam 2 wait-state de la memorie
        tick(1); show("wait mem     ");
        mem_ready = 1;
        tick(1); show("COMPLETE     ");  // do_cache_write=1, cpu_ready=1
        mem_ready = 0;
        tick(1); show("IDLE         ");
        cpu_valid = 0;
        tick(1);

        // ========================================================
        // Scenariu 4: READ MISS, way dirty (evict + fetch)
        // ========================================================
        $display("\n--- Scenariu 4: READ MISS (dirty way → EVICT) ---");
        cpu_valid = 1; cpu_write = 0;
        cache_hit = 0; is_dirty = 1;
        tick(1); show("CHECK_HIT    ");
        tick(1); show("EVICT        ");  // do_mem_write=1
        tick(1); show("wait evict   ");
        mem_ready = 1;
        tick(1); show("ALLOC_FETCH  ");  // do_mem_read=1
        mem_ready = 0;
        tick(1); show("wait fetch   ");
        mem_ready = 1;
        tick(1); show("COMPLETE     ");  // do_cache_write=1, cpu_ready=1
        mem_ready = 0; is_dirty = 0;
        tick(1); show("IDLE         ");
        cpu_valid = 0;
        tick(2);

        $display("\n--- Toate scenariile terminate ---");
        $finish;
    end

endmodule

waves/tb_fsm.vcd
$date
	Fri Jun 12 22:45:49 2026
$end
$version
	Icarus Verilog
$end
$timescale
	1ps
$end
$scope module tb_fsm_controller $end
$var wire 1 ! update_lru $end
$var wire 3 " state_out [2:0] $end
$var wire 1 # set_dirty $end
$var wire 1 $ latch_request $end
$var wire 1 % do_mem_write $end
$var wire 1 & do_mem_read $end
$var wire 1 ' do_cache_write $end
$var wire 1 ( cpu_ready $end
$var reg 1 ) cache_hit $end
$var reg 1 * clk $end
$var reg 1 + cpu_valid $end
$var reg 1 , cpu_write $end
$var reg 1 - is_dirty $end
$var reg 1 . mem_ready $end
$var reg 1 / rst $end
$scope module dut $end
$var wire 1 ) cache_hit $end
$var wire 1 * clk $end
$var wire 1 + cpu_valid $end
$var wire 1 , cpu_write $end
$var wire 1 - is_dirty $end
$var wire 1 . mem_ready $end
$var wire 1 / rst $end
$var wire 3 0 state_out [2:0] $end
$var parameter 3 1 ALLOCATE_FETCH $end
$var parameter 3 2 CHECK_HIT $end
$var parameter 3 3 COMPLETE $end
$var parameter 3 4 EVICT $end
$var parameter 3 5 IDLE $end
$var parameter 3 6 READ_HIT $end
$var parameter 3 7 WRITE_HIT $end
$var reg 1 ( cpu_ready $end
$var reg 1 ' do_cache_write $end
$var reg 1 & do_mem_read $end
$var reg 1 % do_mem_write $end
$var reg 1 $ latch_request $end
$var reg 3 8 next_state [2:0] $end
$var reg 1 9 pending_write $end
$var reg 1 # set_dirty $end
$var reg 3 : state [2:0] $end
$var reg 1 ! update_lru $end
$upscope $end
$scope task show $end
$var reg 128 ; label [127:0] $end
$upscope $end
$scope task tick $end
$var integer 32 < k [31:0] $end
$var integer 32 = n [31:0] $end
$upscope $end
$upscope $end
$enddefinitions $end
$comment Show the parameter values. $end
$dumpall
b11 7
b10 6
b0 5
b100 4
b110 3
b1 2
b101 1
$end
#0
$dumpvars
b10 =
b0 <
bx ;
bx :
x9
b0 8
bx 0
1/
0.
0-
0,
0+
0*
0)
0(
0'
0&
0%
0$
0#
bx "
0!
$end
#5000
09
b0 "
b0 0
b0 :
b1 <
1*
#10000
0*
#15000
b10 <
1*
#16000
b1 8
1$
b0 <
b1 =
b10010010100010001001100010001010010101101110010011001010111000100100000 ;
1)
1+
0/
#20000
0*
#25000
b10 8
0$
b1 "
b1 0
b1 :
b1 <
1*
#26000
b0 <
b10000110100100001000101010000110100101101011111010010000100100101010100 ;
#30000
0*
#35000
b0 8
1(
1!
b10 "
b10 0
b10 :
b1 <
1*
#36000
b0 <
b10100100100010101000001010001000101111101001000010010010101010000100000 ;
#40000
0*
#45000
b1 8
1$
0(
0!
b0 "
b0 0
b0 :
b1 <
1*
#46000
0$
b0 8
b0 <
0+
b10010010100010001001100010001010010000000100000001000000010000000100000 ;
#50000
0*
#55000
b1 <
1*
#56000
b1 8
1$
b0 <
1,
1+
#60000
0*
#65000
b11 8
0$
19
b1 "
b1 0
b1 :
b1 <
1*
#66000
b0 <
b10000110100100001000101010000110100101101011111010010000100100101010100 ;
#70000
0*
#75000
b0 8
1(
1!
1#
1'
b11 "
b11 0
b11 :
b1 <
1*
#76000
b0 <
b10101110101001001001001010101000100010101011111010010000100100101010100 ;
#80000
0*
#85000
b1 8
1$
0(
0#
0!
0'
b0 "
b0 0
b0 :
b1 <
1*
#86000
0$
b0 8
b0 <
0,
0+
b10010010100010001001100010001010010000000100000001000000010000000100000 ;
#90000
0*
#95000
b1 <
1*
#96000
b1 8
1$
b0 <
0)
1+
#100000
0*
#105000
b101 8
0$
09
b1 "
b1 0
b1 :
b1 <
1*
#106000
b0 <
b1000011010010000100010101000011010010110101111101001000010010010101010000100000001000000010000000100000 ;
#110000
0*
#115000
1&
b101 "
b101 0
b101 :
b1 <
1*
#116000
b0 <
b1000001010011000100110001001111010000110101111101000110010001010101010001000011010010000010000000100000 ;
#120000
0*
#125000
b1 <
1*
#126000
b110 8
1&
b0 <
1.
b1110111011000010110100101110100001000000110110101100101011011010010000000100000001000000010000000100000 ;
#130000
0*
#135000
b0 8
1(
1!
1'
0&
b110 "
b110 0
b110 :
b1 <
1*
#136000
1(
1!
1'
b0 8
b0 <
0.
b1000011010011110100110101010000010011000100010101010100010001010010000000100000001000000010000000100000 ;
#140000
0*
#145000
b1 8
1$
0(
0!
0'
b0 "
b0 0
b0 :
b1 <
1*
#146000
0$
b0 8
b0 <
0+
b1001001010001000100110001000101001000000010000000100000001000000010000000100000001000000010000000100000 ;
#150000
0*
#155000
b1 <
1*
#156000
b1 8
1$
b0 <
1-
1+
#160000
0*
#165000
b100 8
0$
b1 "
b1 0
b1 :
b1 <
1*
#166000
b0 <
b1000011010010000100010101000011010010110101111101001000010010010101010000100000001000000010000000100000 ;
#170000
0*
#175000
1%
b100 "
b100 0
b100 :
b1 <
1*
#176000
b0 <
b1000101010101100100100101000011010101000010000000100000001000000010000000100000001000000010000000100000 ;
#180000
0*
#185000
b1 <
1*
#186000
b101 8
1%
b0 <
1.
b1110111011000010110100101110100001000000110010101110110011010010110001101110100001000000010000000100000 ;
#190000
0*
#195000
b110 8
1&
0%
b101 "
b101 0
b101 :
b1 <
1*
#196000
1&
b101 8
b0 <
0.
b1000001010011000100110001001111010000110101111101000110010001010101010001000011010010000010000000100000 ;
#200000
0*
#205000
b1 <
1*
#206000
b110 8
1&
b0 <
1.
b1110111011000010110100101110100001000000110011001100101011101000110001101101000001000000010000000100000 ;
#210000
0*
#215000
b0 8
1(
1!
1'
0&
b110 "
b110 0
b110 :
b1 <
1*
#216000
1(
1!
1'
b0 8
b0 <
0-
0.
b1000011010011110100110101010000010011000100010101010100010001010010000000100000001000000010000000100000 ;
#220000
0*
#225000
b1 8
1$
0(
0!
0'
b0 "
b0 0
b0 :
b1 <
1*
#226000
0$
b0 8
b0 <
b10 =
0+
b1001001010001000100110001000101001000000010000000100000001000000010000000100000001000000010000000100000 ;
#230000
0*
#235000
b1 <
1*
#240000
0*
#245000
b10 <
1*
