src/lru_tracker.v

// tine evidența ordinii de acces pentru politica LRU
// pt fiecare set o sa stie care way n a mai fost folost de mult
// fiecare way primeste un nr/varsta de la 1 la 3 cu 0 = cel mai recent folosit, 3 = cel mai demult folosit -la asta se verif dirty si s ar putea sa fie evacuat. basically candideaza

// cand accesăm un way, el devine 0 și restul îmbătrânesc :))

module lru_tracker (
    input  wire       clk,
    input  wire       rst,

    // date de la fsm
    input  wire       update_en,    // 1 - actualiz dupa acces un way
    input  wire [6:0] set_index,    // care set actualizăm
    input  wire [1:0] way_used,     // care way tocmai a fost accesat

    // spre fsm
  output reg  [1:0] lru_way       // way-ul cel mai batran din setul cerut
);

    
    // age[set][way] = cât de "bătrân" e way-ul
    reg [1:0] age [0:127][0:3];

    integer i, j;

  // gasim way ul LRU (cel mai batran)
    // FSM-ul vede mereu care e candidatul pentru evacuare
    always @(*) begin
        // Pornim cu way 0 ca și candidat
        lru_way = 2'd0;

        // Comparăm cu celelalte way-uri
        if (age[set_index][1] > age[set_index][lru_way])
            lru_way = 2'd1;
        if (age[set_index][2] > age[set_index][lru_way])
            lru_way = 2'd2;
        if (age[set_index][3] > age[set_index][lru_way])
            lru_way = 2'd3;
    end

    // actualizam varste cum am zis
    always @(posedge clk) begin
        if (rst) begin
            // La reset, dăm vârste inițiale diferite
            // way 0 = cel mai recent, way 3 = cel mai old
            for (i = 0; i < 128; i = i + 1)
                for (j = 0; j < 4; j = j + 1)
                    age[i][j] <= j[1:0];  // 0, 1, 2, 3
        end

        else if (update_en) begin
            // way_used devine cel mai recent (vârsta 0)
            // orice way mai tânăr decât way_used îmbătrânește cu 1
            

            age[set_index][way_used] <= 2'd0;

            if (way_used != 2'd0 && age[set_index][0] < age[set_index][way_used])
                age[set_index][0] <= age[set_index][0] + 1;

            if (way_used != 2'd1 && age[set_index][1] < age[set_index][way_used])
                age[set_index][1] <= age[set_index][1] + 1;

            if (way_used != 2'd2 && age[set_index][2] < age[set_index][way_used])
                age[set_index][2] <= age[set_index][2] + 1;

            if (way_used != 2'd3 && age[set_index][3] < age[set_index][way_used])
                age[set_index][3] <= age[set_index][3] + 1;
        end
    end

endmodule

tb/tb_lru_logic.v
// Testbench izolat pentru lru_tracker
// Verifica explicit ca ordinea de evacuare LRU este corecta dupa secvente de acces
//
// Logica lru_tracker:
//   - age[set][way] = 0 → cel mai recent accesat
//   - age[set][way] = 3 → cel mai vechi (candidat LRU)
//   - La acces way X: age[X]=0, way-urile mai tinere (age < age_vechi[X]) imbatranesc cu 1

`timescale 1ns/1ps

module tb_lru_logic;

    reg        clk, rst;
    reg        update_en;
    reg  [6:0] set_index;
    reg  [1:0] way_used;
    wire [1:0] lru_way;

    lru_tracker dut (
        .clk       (clk),
        .rst       (rst),
        .update_en (update_en),
        .set_index (set_index),
        .way_used  (way_used),
        .lru_way   (lru_way)
    );

    initial clk = 0;
    always #5 clk = ~clk;

    // Acceseaza un way si asteapta un ciclu
    task access;
        input [1:0] w;
        begin
            @(negedge clk);
            update_en = 1;
            way_used  = w;
            @(posedge clk); #1;
            update_en = 0;
        end
    endtask

    // Verifica LRU si afiseaza rezultatul
    task check_lru;
        input [1:0] expected;
        input [63:0] label;
        begin
            @(negedge clk); #1;
            if (lru_way === expected)
                $display("PASS  %s | lru_way=%0d (expected %0d)", label, lru_way, expected);
            else
                $display("FAIL  %s | lru_way=%0d (expected %0d) !!!", label, lru_way, expected);
        end
    endtask

    integer i;

    initial begin
        $dumpfile("waves/tb_lru.vcd");
        $dumpvars(0, tb_lru_logic);

        // Reset
        rst = 1; update_en = 0; set_index = 0; way_used = 0;
        @(posedge clk); #1;
        @(posedge clk); #1;
        rst = 0;

        // Dupa reset: age = [0,1,2,3] → way 3 e LRU
        $display("\n--- Dupa reset (set 0) ---");
        check_lru(2'd3, "initial LRU");

        // ============================================================
        // Test 1: Acces secvential 0→1→2→3
        // Dupa acces way 0: ages=[0,2,3,1]? Sa vedem
        // ============================================================
        $display("\n--- Test 1: acces secvential way 0,1,2,3 ---");
        set_index = 0;

        access(2'd0); // accesat: 0  → age[0]=0, restul imbatranesc cei cu age<age_vechi[0]=0 → nimeni
                      // ages: [0,1,2,3]→ [0,1,2,3] (way 0 era deja cel mai tanar)
        check_lru(2'd3, "dupa access(0)   ");

        access(2'd1); // age[1] era 1 → age[1]=0, way 0 (age=0 < 1) → age[0]++
                      // ages: [1,0,2,3]
        check_lru(2'd3, "dupa access(1)   ");

        access(2'd2); // age[2] era 2 → age[2]=0, way 0 (1<2)→+1, way 1 (0<2)→+1
                      // ages: [2,1,0,3]
        check_lru(2'd3, "dupa access(2)   ");

        access(2'd3); // age[3] era 3 → age[3]=0, way 0(2<3)→+1, way 1(1<3)→+1, way 2(0<3)→+1
                      // ages: [3,2,1,0]
        check_lru(2'd0, "dupa access(3)   "); // way 0 e acum LRU

        // ============================================================
        // Test 2: Re-acces way 0 → way 0 devine cel mai tanar
        // ============================================================
        $display("\n--- Test 2: re-acces way 0 (trebuie sa nu mai fie LRU) ---");
        access(2'd0); // age[0] era 3 → age[0]=0, restul (age<3) imbatranesc
                      // ages: [0,3,2,1]
        check_lru(2'd1, "dupa re-access(0)"); // way 1 (age=3) e acum LRU

        // ============================================================
        // Test 3: Acces repetat pe acelasi way → LRU nu se schimba
        // ============================================================
        $display("\n--- Test 3: acces repetat way 0 (LRU ramane acelasi) ---");
        access(2'd0);
        access(2'd0);
        access(2'd0);
        check_lru(2'd1, "dupa 3x access(0)"); // way 1 ramane LRU

        // ============================================================
        // Test 4: Set diferit (set 5) — nu afecteaza set 0
        // ============================================================
        $display("\n--- Test 4: acces pe set 5, verificam ca set 0 e neafectat ---");
        set_index = 5;
        access(2'd2);
        access(2'd3);
        set_index = 0;
        check_lru(2'd1, "set0 neafectat   "); // set 0 pastrat din test 3

        // ============================================================
        // Test 5: Rotatie completa — fiecare way devine LRU pe rand
        // ============================================================
        $display("\n--- Test 5: rotatie 3,2,1,0 → LRU in ordine inversa ---");
        set_index = 7;
        // reset indirect: acces in ordine 0,1,2,3 → ages=[3,2,1,0]
        access(2'd0); access(2'd1); access(2'd2); access(2'd3);
        check_lru(2'd0, "lru dupa 0123    "); // way 0 e LRU

        access(2'd0); // accesam LRU-ul
        check_lru(2'd1, "lru dupa +acc(0) "); // way 1 devine LRU

        access(2'd1);
        check_lru(2'd2, "lru dupa +acc(1) ");

        access(2'd2);
        check_lru(2'd3, "lru dupa +acc(2) ");

        access(2'd3);
        check_lru(2'd0, "lru dupa +acc(3) ");

        #20;
        $display("\n--- Testbench LRU finalizat ---");
        $finish;
    end

endmodule

waves/tb_lru.vcd
$date
	Fri Jun 12 23:08:58 2026
$end
$version
	Icarus Verilog
$end
$timescale
	1ps
$end
$scope module tb_lru_logic $end
$var wire 2 ! lru_way [1:0] $end
$var reg 1 " clk $end
$var reg 1 # rst $end
$var reg 7 $ set_index [6:0] $end
$var reg 1 % update_en $end
$var reg 2 & way_used [1:0] $end
$scope module dut $end
$var wire 1 " clk $end
$var wire 1 # rst $end
$var wire 7 ' set_index [6:0] $end
$var wire 1 % update_en $end
$var wire 2 ( way_used [1:0] $end
$var reg 2 ) lru_way [1:0] $end
$var integer 32 * i [31:0] $end
$var integer 32 + j [31:0] $end
$upscope $end
$scope task access $end
$var reg 2 , w [1:0] $end
$upscope $end
$scope task check_lru $end
$var reg 2 - expected [1:0] $end
$var reg 64 . label [63:0] $end
$upscope $end
$upscope $end
$enddefinitions $end
$comment Show the parameter values. $end
$dumpall
$end
#0
$dumpvars
bx .
bx -
bx ,
bx +
bx *
b0 )
b0 (
b0 '
b0 &
0%
b0 $
1#
0"
b0 !
$end
#5000
b11 !
b11 )
b100 +
b10000000 *
1"
#10000
0"
#15000
b100 +
b10000000 *
1"
#16000
b111010001101001011000010110110000100000010011000101001001010101 .
b11 -
0#
#20000
0"
#21000
b0 ,
#25000
1"
#30000
1%
0"
#35000
1"
#36000
b111001101110011001010000011000000101001001000000010000000100000 .
0%
#40000
0"
#41000
b1 ,
#45000
1"
#50000
b1 &
b1 (
1%
0"
#55000
b11 !
b11 )
1"
#56000
b111001101110011001010000011000100101001001000000010000000100000 .
0%
#60000
0"
#61000
b10 ,
#65000
1"
#70000
b10 &
b10 (
1%
0"
#75000
b11 !
b11 )
1"
#76000
b111001101110011001010000011001000101001001000000010000000100000 .
0%
#80000
0"
#81000
b11 ,
#85000
1"
#90000
b11 &
b11 (
1%
0"
#95000
b0 !
b0 )
1"
#96000
b111001101110011001010000011001100101001001000000010000000100000 .
b0 -
0%
#100000
0"
#101000
b0 ,
#105000
1"
#110000
b0 &
b0 (
1%
0"
#115000
b1 !
b1 )
1"
#116000
b110001101100011011001010111001101110011001010000011000000101001 .
b1 -
0%
#120000
0"
#125000
1"
#130000
1%
0"
#135000
1"
#136000
0%
#140000
1%
0"
#145000
1"
#146000
0%
#150000
1%
0"
#155000
1"
#156000
0%
#160000
0"
#161000
b11 !
b11 )
b10 ,
b101 $
b101 '
#165000
1"
#170000
b10 &
b10 (
1%
0"
#175000
b11 !
b11 )
1"
#176000
b11 ,
0%
#180000
b11 &
b11 (
1%
0"
#185000
b1 !
b1 )
1"
#186000
b1 !
b1 )
b110010101100011011101000110000101110100001000000010000000100000 .
b0 $
b0 '
0%
#190000
0"
#191000
b11 !
b11 )
b0 ,
b111 $
b111 '
#195000
1"
#200000
b0 &
b0 (
1%
0"
#205000
1"
#206000
b1 ,
0%
#210000
b1 &
b1 (
1%
0"
#215000
b11 !
b11 )
1"
#216000
b10 ,
0%
#220000
b10 &
b10 (
1%
0"
#225000
b11 !
b11 )
1"
#226000
b11 ,
0%
#230000
b11 &
b11 (
1%
0"
#235000
b0 !
b0 )
1"
#236000
b11000000110001001100100011001100100000001000000010000000100000 .
b0 -
0%
#240000
0"
#241000
b0 ,
#245000
1"
#250000
b0 &
b0 (
1%
0"
#255000
b1 !
b1 )
1"
#256000
b10101101100001011000110110001100101000001100000010100100100000 .
b1 -
0%
#260000
0"
#261000
b1 ,
#265000
1"
#270000
b1 &
b1 (
1%
0"
#275000
b10 !
b10 )
1"
#276000
b10101101100001011000110110001100101000001100010010100100100000 .
b10 -
0%
#280000
0"
#281000
b10 ,
#285000
1"
#290000
b10 &
b10 (
1%
0"
#295000
b11 !
b11 )
1"
#296000
b10101101100001011000110110001100101000001100100010100100100000 .
b11 -
0%
#300000
0"
#301000
b11 ,
#305000
1"
#310000
b11 &
b11 (
1%
0"
#315000
b0 !
b0 )
1"
#316000
b10101101100001011000110110001100101000001100110010100100100000 .
b0 -
0%
